license.S.HTML
venue.S.HTML
factory_farm/BrightAgrotech--vertical-farm-916337_1920.jpg
factory_farm/___itinerary/itinerary - breaking.S.HTML
factory_farm/___itinerary/itinerary.S.HTML
factory_farm/___itinerary/maybes.s.HTML
factory_farm/___itinerary/processes/errout/script.py
factory_farm/___itinerary/processes/errout/start.py
factory_farm/___itinerary/processes/errout_v1/script.py
factory_farm/___itinerary/processes/errout_v1/start.py
factory_farm/___itinerary/processes/errout_v2/script.py
factory_farm/___itinerary/processes/errout_v2/start.py
factory_farm/__bin/factory_farm_1
factory_farm/__init__.py
factory_farm/__license/options/gpl-3.0-standalone.html
factory_farm/_book/advanced tutorial.s.HTML
factory_farm/_book/book.s.HTML
factory_farm/_book/relevant.s.HTML
factory_farm/_clique/__init__.py
factory_farm/_clique/group/__init__.py
factory_farm/_status/--statuspy.py
factory_farm/_status/DB/records.json
factory_farm/_status/establish.py
factory_farm/_status/monitors/-1_start/chassis/modules/monitor_1.py
factory_farm/_status/monitors/-1_start/status_1.py
factory_farm/_status/monitors/0_start/chassis/modules/monitor_1.py
factory_farm/_status/monitors/0_start/status_1.py
factory_farm/_status/monitors/1/stasis/path_1_health.py
factory_farm/_status/monitors/1/stasis/path_2_health.py
factory_farm/_status/monitors/1/status_1.py
factory_farm/_status/monitors/10_time_limits/guarantees/guarantee_1.py
factory_farm/_status/monitors/10_time_limits/status_1.py
factory_farm/_status/monitors/2/stasis/1_health.py
factory_farm/_status/monitors/2/stasis/2_health.py
factory_farm/_status/monitors/2/stasis/modules/MODULE_1.py
factory_farm/_status/monitors/2/status_1.py
factory_farm/_status/monitors/3_empty_glob/status_1.py
factory_farm/_status/monitors/4.1_bad_import/stasis/1_health.py
factory_farm/_status/monitors/4.1_bad_import/status_1.py
factory_farm/_status/monitors/4_bad_import/stasis/1_health.py
factory_farm/_status/monitors/4_bad_import/status_1.py
factory_farm-1.2.6.dist-info/METADATA
factory_farm-1.2.6.dist-info/WHEEL
factory_farm-1.2.6.dist-info/entry_points.txt
factory_farm-1.2.6.dist-info/RECORD
